Workbook

Sheet Productos
A1: Referencia | B1: Producto | C1: Categoría | D1: Subcategoría | E1: Marca | F1: Colores | G1: Unidades | H1: Costo proveedor (COP) | I1: Margen | J1: Precio sin redondear | K1: Precio de venta (COP) | L1: Ganancia por unidad | M1: Margen real | N1: Foto | O1: Imagen | P1: Archivo de imagen
A2: CON-NSW2 | B2: Nintendo Switch 2 | C2: TV y consolas | D2: Consolas | E2: Nintendo | F2: Negro | G2: Sin control | H2: 1900000 | I2: =INDEX(Márgenes!$C$7:$C$23,MATCH(D2,Márgenes!$B$7:$B$23,0)) | J2: =MAX(H2*(1+I2),H2+Márgenes!$B$4) | K2: =IF(J2<1000000,CEILING(J2,1000),CEILING(J2,10000))-100 | L2: =K2-H2 | M2: =IF(K2=0,0,L2/K2) | O2: Lista | P2: imagenes/CON-NSW2.jpg
A3: CON-PS5SLIM-1TB | B3: Sony PlayStation 5 Slim Edición Disco Físico 1TB | C3: TV y consolas | D3: Consolas | E3: Sony | G3: Sin control | H3: 2800000 | I3: =INDEX(Márgenes!$C$7:$C$23,MATCH(D3,Márgenes!$B$7:$B$23,0)) | J3: =MAX(H3*(1+I3),H3+Márgenes!$B$4) | K3: =IF(J3<1000000,CEILING(J3,1000),CEILING(J3,10000))-100 | L3: =K3-H3 | M3: =IF(K3=0,0,L3/K3) | O3: Lista | P3: imagenes/CON-PS5SLIM-1TB.jpg
A4: TAB-ACER-A10 | B4: Acer Iconia A10 10" 4GB+64GB | C4: Celulares y tablets | D4: Tablets | E4: Acer | F4: Negro | G4: Sin control | H4: 325000 | I4: =INDEX(Márgenes!$C$7:$C$23,MATCH(D4,Márgenes!$B$7:$B$23,0)) | J4: =MAX(H4*(1+I4),H4+Márgenes!$B$4) | K4: =IF(J4<1000000,CEILING(J4,1000),CEILING(J4,10000))-100 | L4: =K4-H4 | M4: =IF(K4=0,0,L4/K4) | O4: Lista | P4: imagenes/TAB-ACER-A10.jpg
A5: ZTE-A56PRO-4-128 | B5: ZTE A56 Pro 4GB+128GB | C5: Celulares y tablets | D5: Celulares | E5: ZTE | F5: Dorado/Amarillo, Blanco | G5: Sin control | H5: 345000 | I5: =INDEX(Márgenes!$C$7:$C$23,MATCH(D5,Márgenes!$B$7:$B$23,0)) | J5: =MAX(H5*(1+I5),H5+Márgenes!$B$4) | K5: =IF(J5<1000000,CEILING(J5,1000),CEILING(J5,10000))-100 | L5: =K5-H5 | M5: =IF(K5=0,0,L5/K5) | O5: Lista | P5: imagenes/ZTE-A56PRO-4-128.jpg
A6: ZTE-A35E-2-64 | B6: ZTE A35E 2GB+64GB | C6: Celulares y tablets | D6: Celulares | E6: ZTE | F6: Verde, Blanco | G6: Sin control | H6: 270000 | I6: =INDEX(Márgenes!$C$7:$C$23,MATCH(D6,Márgenes!$B$7:$B$23,0)) | J6: =MAX(H6*(1+I6),H6+Márgenes!$B$4) | K6: =IF(J6<1000000,CEILING(J6,1000),CEILING(J6,10000))-100 | L6: =K6-H6 | M6: =IF(K6=0,0,L6/K6) | O6: Lista | P6: imagenes/ZTE-A35E-2-64.jpg
A7: ZTE-V80MAX-4-256 | B7: ZTE Nubia V80 Max 4GB+256GB | C7: Celulares y tablets | D7: Celulares | E7: ZTE | F7: Negro | G7: Sin control | H7: 465000 | I7: =INDEX(Márgenes!$C$7:$C$23,MATCH(D7,Márgenes!$B$7:$B$23,0)) | J7: =MAX(H7*(1+I7),H7+Márgenes!$B$4) | K7: =IF(J7<1000000,CEILING(J7,1000),CEILING(J7,10000))-100 | L7: =K7-H7 | M7: =IF(K7=0,0,L7/K7) | O7: Lista | P7: imagenes/ZTE-V80MAX-4-256.jpg
A8: ZTE-A75-4-256 | B8: ZTE Blade A75 4GB+256GB | C8: Celulares y tablets | D8: Celulares | E8: ZTE | F8: Negro | G8: Sin control | H8: 395000 | I8: =INDEX(Márgenes!$C$7:$C$23,MATCH(D8,Márgenes!$B$7:$B$23,0)) | J8: =MAX(H8*(1+I8),H8+Márgenes!$B$4) | K8: =IF(J8<1000000,CEILING(J8,1000),CEILING(J8,10000))-100 | L8: =K8-H8 | M8: =IF(K8=0,0,L8/K8) | O8: Lista | P8: imagenes/ZTE-A75-4-256.jpg
A9: HON-X5CPLUS-4-256 | B9: Honor X5C Plus 4GB+256GB | C9: Celulares y tablets | D9: Celulares | E9: Honor | F9: Blanco | G9: Sin control | H9: 420000 | I9: =INDEX(Márgenes!$C$7:$C$23,MATCH(D9,Márgenes!$B$7:$B$23,0)) | J9: =MAX(H9*(1+I9),H9+Márgenes!$B$4) | K9: =IF(J9<1000000,CEILING(J9,1000),CEILING(J9,10000))-100 | L9: =K9-H9 | M9: =IF(K9=0,0,L9/K9) | O9: Lista | P9: imagenes/HON-X5CPLUS-4-256.jpg
A10: HON-T10-4-64 | B10: Honor Choice T10 4GB+64GB | C10: Celulares y tablets | D10: Tablets | E10: Honor | F10: Blanco | G10: Sin control | H10: 280000 | I10: =INDEX(Márgenes!$C$7:$C$23,MATCH(D10,Márgenes!$B$7:$B$23,0)) | J10: =MAX(H10*(1+I10),H10+Márgenes!$B$4) | K10: =IF(J10<1000000,CEILING(J10,1000),CEILING(J10,10000))-100 | L10: =K10-H10 | M10: =IF(K10=0,0,L10/K10) | O10: Lista | P10: imagenes/HON-T10-4-64.jpg
A11: HON-PLAY10-3-64 | B11: Honor Play 10 3GB+64GB | C11: Celulares y tablets | D11: Celulares | E11: Honor | F11: Negro, Azul | G11: Sin control | H11: 320000 | I11: =INDEX(Márgenes!$C$7:$C$23,MATCH(D11,Márgenes!$B$7:$B$23,0)) | J11: =MAX(H11*(1+I11),H11+Márgenes!$B$4) | K11: =IF(J11<1000000,CEILING(J11,1000),CEILING(J11,10000))-100 | L11: =K11-H11 | M11: =IF(K11=0,0,L11/K11) | O11: Lista | P11: imagenes/HON-PLAY10-3-64.jpg
A12: HON-400SMART-6-256 | B12: Honor 400 Smart 6GB+256GB | C12: Celulares y tablets | D12: Celulares | E12: Honor | F12: Dorado/Amarillo, Blanco | G12: Sin control | H12: 640000 | I12: =INDEX(Márgenes!$C$7:$C$23,MATCH(D12,Márgenes!$B$7:$B$23,0)) | J12: =MAX(H12*(1+I12),H12+Márgenes!$B$4) | K12: =IF(J12<1000000,CEILING(J12,1000),CEILING(J12,10000))-100 | L12: =K12-H12 | M12: =IF(K12=0,0,L12/K12) | O12: Lista | P12: imagenes/HON-400SMART-6-256.jpg
A13: INF-SMART20-4-64 | B13: Infinix Smart 20 4GB+64GB | C13: Celulares y tablets | D13: Celulares | E13: Infinix | F13: Naranja | G13: Sin control | H13: 395000 | I13: =INDEX(Márgenes!$C$7:$C$23,MATCH(D13,Márgenes!$B$7:$B$23,0)) | J13: =MAX(H13*(1+I13),H13+Márgenes!$B$4) | K13: =IF(J13<1000000,CEILING(J13,1000),CEILING(J13,10000))-100 | L13: =K13-H13 | M13: =IF(K13=0,0,L13/K13) | O13: Lista | P13: imagenes/INF-SMART20-4-64.jpg
A14: INF-SMART20-4-128 | B14: Infinix Smart 20 4GB+128GB | C14: Celulares y tablets | D14: Celulares | E14: Infinix | F14: Naranja | G14: Sin control | H14: 430000 | I14: =INDEX(Márgenes!$C$7:$C$23,MATCH(D14,Márgenes!$B$7:$B$23,0)) | J14: =MAX(H14*(1+I14),H14+Márgenes!$B$4) | K14: =IF(J14<1000000,CEILING(J14,1000),CEILING(J14,10000))-100 | L14: =K14-H14 | M14: =IF(K14=0,0,L14/K14) | O14: Lista | P14: imagenes/INF-SMART20-4-128.jpg
A15: INF-HOT70-4-128 | B15: Infinix Hot 70 4GB+128GB | C15: Celulares y tablets | D15: Celulares | E15: Infinix | F15: Azul | G15: Sin control | H15: 519900 | I15: =INDEX(Márgenes!$C$7:$C$23,MATCH(D15,Márgenes!$B$7:$B$23,0)) | J15: =MAX(H15*(1+I15),H15+Márgenes!$B$4) | K15: =IF(J15<1000000,CEILING(J15,1000),CEILING(J15,10000))-100 | L15: =K15-H15 | M15: =IF(K15=0,0,L15/K15) | O15: Lista | P15: imagenes/INF-HOT70-4-128.jpg
A16: TEC-SPARKGO3-4-128 | B16: Tecno Spark Go 3 4GB+128GB | C16: Celulares y tablets | D16: Celulares | E16: Tecno | G16: Sin control | H16: 380000 | I16: =INDEX(Márgenes!$C$7:$C$23,MATCH(D16,Márgenes!$B$7:$B$23,0)) | J16: =MAX(H16*(1+I16),H16+Márgenes!$B$4) | K16: =IF(J16<1000000,CEILING(J16,1000),CEILING(J16,10000))-100 | L16: =K16-H16 | M16: =IF(K16=0,0,L16/K16) | O16: Lista | P16: imagenes/TEC-SPARKGO3-4-128.jpg
A17: MOT-G06-4-128 | B17: Motorola Moto G06 4GB+128GB | C17: Celulares y tablets | D17: Celulares | E17: Motorola | F17: Azul | G17: Sin control | H17: 375000 | I17: =INDEX(Márgenes!$C$7:$C$23,MATCH(D17,Márgenes!$B$7:$B$23,0)) | J17: =MAX(H17*(1+I17),H17+Márgenes!$B$4) | K17: =IF(J17<1000000,CEILING(J17,1000),CEILING(J17,10000))-100 | L17: =K17-H17 | M17: =IF(K17=0,0,L17/K17) | O17: Lista | P17: imagenes/MOT-G06-4-128.jpg
A18: MOT-G17-4-128 | B18: Motorola Moto G17 4GB+128GB | C18: Celulares y tablets | D18: Celulares | E18: Motorola | F18: Morado | G18: Sin control | H18: 440000 | I18: =INDEX(Márgenes!$C$7:$C$23,MATCH(D18,Márgenes!$B$7:$B$23,0)) | J18: =MAX(H18*(1+I18),H18+Márgenes!$B$4) | K18: =IF(J18<1000000,CEILING(J18,1000),CEILING(J18,10000))-100 | L18: =K18-H18 | M18: =IF(K18=0,0,L18/K18) | O18: Lista | P18: imagenes/MOT-G17-4-128.jpg
A19: MOT-EDGE60F-8-256 | B19: Motorola Edge 60 Fusion 5G 8GB+256GB | C19: Celulares y tablets | D19: Celulares | E19: Motorola | G19: Sin control | H19: 900000 | I19: =INDEX(Márgenes!$C$7:$C$23,MATCH(D19,Márgenes!$B$7:$B$23,0)) | J19: =MAX(H19*(1+I19),H19+Márgenes!$B$4) | K19: =IF(J19<1000000,CEILING(J19,1000),CEILING(J19,10000))-100 | L19: =K19-H19 | M19: =IF(K19=0,0,L19/K19) | O19: Lista | P19: imagenes/MOT-EDGE60F-8-256.jpg
A20: MOT-EDGE70F-12-256 | B20: Motorola Edge 70 Fusion 5G 12GB+256GB | C20: Celulares y tablets | D20: Celulares | E20: Motorola | F20: Verde, Azul | G20: Sin control | H20: 1280000 | I20: =INDEX(Márgenes!$C$7:$C$23,MATCH(D20,Márgenes!$B$7:$B$23,0)) | J20: =MAX(H20*(1+I20),H20+Márgenes!$B$4) | K20: =IF(J20<1000000,CEILING(J20,1000),CEILING(J20,10000))-100 | L20: =K20-H20 | M20: =IF(K20=0,0,L20/K20) | O20: Lista | P20: imagenes/MOT-EDGE70F-12-256.jpg
A21: SAM-A37-6-128 | B21: Samsung Galaxy A37 5G 6GB+128GB | C21: Celulares y tablets | D21: Celulares | E21: Samsung | F21: Morado, Negro | G21: Sin control | H21: 837000 | I21: =INDEX(Márgenes!$C$7:$C$23,MATCH(D21,Márgenes!$B$7:$B$23,0)) | J21: =MAX(H21*(1+I21),H21+Márgenes!$B$4) | K21: =IF(J21<1000000,CEILING(J21,1000),CEILING(J21,10000))-100 | L21: =K21-H21 | M21: =IF(K21=0,0,L21/K21) | O21: Lista | P21: imagenes/SAM-A37-6-128.jpg
A22: SAM-A37-8-256 | B22: Samsung Galaxy A37 5G 8GB+256GB | C22: Celulares y tablets | D22: Celulares | E22: Samsung | F22: Negro | G22: Sin control | H22: 1025000 | I22: =INDEX(Márgenes!$C$7:$C$23,MATCH(D22,Márgenes!$B$7:$B$23,0)) | J22: =MAX(H22*(1+I22),H22+Márgenes!$B$4) | K22: =IF(J22<1000000,CEILING(J22,1000),CEILING(J22,10000))-100 | L22: =K22-H22 | M22: =IF(K22=0,0,L22/K22) | O22: Lista | P22: imagenes/SAM-A37-8-256.jpg
A23: XIA-REDMI15-8-256 | B23: Xiaomi Redmi 15 8GB+256GB | C23: Celulares y tablets | D23: Celulares | E23: Xiaomi | F23: Blanco | G23: Sin control | H23: 590000 | I23: =INDEX(Márgenes!$C$7:$C$23,MATCH(D23,Márgenes!$B$7:$B$23,0)) | J23: =MAX(H23*(1+I23),H23+Márgenes!$B$4) | K23: =IF(J23<1000000,CEILING(J23,1000),CEILING(J23,10000))-100 | L23: =K23-H23 | M23: =IF(K23=0,0,L23/K23) | O23: Lista | P23: imagenes/XIA-REDMI15-8-256.jpg
A24: XIA-REDMI17-4-128 | B24: Xiaomi Redmi 17 4GB+128GB | C24: Celulares y tablets | D24: Celulares | E24: Xiaomi | F24: Negro | G24: Sin control | H24: 480000 | I24: =INDEX(Márgenes!$C$7:$C$23,MATCH(D24,Márgenes!$B$7:$B$23,0)) | J24: =MAX(H24*(1+I24),H24+Márgenes!$B$4) | K24: =IF(J24<1000000,CEILING(J24,1000),CEILING(J24,10000))-100 | L24: =K24-H24 | M24: =IF(K24=0,0,L24/K24) | O24: Lista | P24: imagenes/XIA-REDMI17-4-128.jpg
A25: XIA-REDMI17-4-256 | B25: Xiaomi Redmi 17 4GB+256GB | C25: Celulares y tablets | D25: Celulares | E25: Xiaomi | F25: Negro, Azul | G25: Sin control | H25: 570000 | I25: =INDEX(Márgenes!$C$7:$C$23,MATCH(D25,Márgenes!$B$7:$B$23,0)) | J25: =MAX(H25*(1+I25),H25+Márgenes!$B$4) | K25: =IF(J25<1000000,CEILING(J25,1000),CEILING(J25,10000))-100 | L25: =K25-H25 | M25: =IF(K25=0,0,L25/K25) | O25: Lista | P25: imagenes/XIA-REDMI17-4-256.jpg
A26: XIA-RN17-4G-4-128 | B26: Xiaomi Redmi Note 17 4G 4GB+128GB | C26: Celulares y tablets | D26: Celulares | E26: Xiaomi | F26: Negro | G26: Sin control | H26: 600000 | I26: =INDEX(Márgenes!$C$7:$C$23,MATCH(D26,Márgenes!$B$7:$B$23,0)) | J26: =MAX(H26*(1+I26),H26+Márgenes!$B$4) | K26: =IF(J26<1000000,CEILING(J26,1000),CEILING(J26,10000))-100 | L26: =K26-H26 | M26: =IF(K26=0,0,L26/K26) | O26: Lista | P26: imagenes/XIA-RN17-4G-4-128.jpg
A27: XIA-RN17-4G-6-256 | B27: Xiaomi Redmi Note 17 4G 6GB+256GB | C27: Celulares y tablets | D27: Celulares | E27: Xiaomi | F27: Negro | G27: Sin control | H27: 695000 | I27: =INDEX(Márgenes!$C$7:$C$23,MATCH(D27,Márgenes!$B$7:$B$23,0)) | J27: =MAX(H27*(1+I27),H27+Márgenes!$B$4) | K27: =IF(J27<1000000,CEILING(J27,1000),CEILING(J27,10000))-100 | L27: =K27-H27 | M27: =IF(K27=0,0,L27/K27) | O27: Lista | P27: imagenes/XIA-RN17-4G-6-256.jpg
A28: 55S6C | B28: Televisor TCL 55" LED 4K UHD Google TV | C28: TV y consolas | D28: Televisores | E28: TCL | G28: Sin control | H28: 1469902 | I28: =INDEX(Márgenes!$C$7:$C$23,MATCH(D28,Márgenes!$B$7:$B$23,0)) | J28: =MAX(H28*(1+I28),H28+Márgenes!$B$4) | K28: =IF(J28<1000000,CEILING(J28,1000),CEILING(J28,10000))-100 | L28: =K28-H28 | M28: =IF(K28=0,0,L28/K28) | O28: Lista | P28: imagenes/55S6C.jpg
A29: 65V6C | B29: Televisor TCL 65" LED 4K UHD Google TV | C29: TV y consolas | D29: Televisores | E29: TCL | G29: Sin control | H29: 2050000 | I29: =INDEX(Márgenes!$C$7:$C$23,MATCH(D29,Márgenes!$B$7:$B$23,0)) | J29: =MAX(H29*(1+I29),H29+Márgenes!$B$4) | K29: =IF(J29<1000000,CEILING(J29,1000),CEILING(J29,10000))-100 | L29: =K29-H29 | M29: =IF(K29=0,0,L29/K29) | O29: Lista | P29: imagenes/65V6C.jpg
A30: UN50U8000FPXPA | B30: Televisor Samsung 50" Crystal UHD 4K U8000F | C30: TV y consolas | D30: Televisores | E30: Samsung | G30: Sin control | H30: 1299900 | I30: =INDEX(Márgenes!$C$7:$C$23,MATCH(D30,Márgenes!$B$7:$B$23,0)) | J30: =MAX(H30*(1+I30),H30+Márgenes!$B$4) | K30: =IF(J30<1000000,CEILING(J30,1000),CEILING(J30,10000))-100 | L30: =K30-H30 | M30: =IF(K30=0,0,L30/K30) | O30: Lista | P30: imagenes/UN50U8000FPXPA.jpg
A31: UN50U8000HPXPA | B31: Televisor Samsung 50" Crystal UHD 4K U8000H | C31: TV y consolas | D31: Televisores | E31: Samsung | G31: Sin control | H31: 1399900 | I31: =INDEX(Márgenes!$C$7:$C$23,MATCH(D31,Márgenes!$B$7:$B$23,0)) | J31: =MAX(H31*(1+I31),H31+Márgenes!$B$4) | K31: =IF(J31<1000000,CEILING(J31,1000),CEILING(J31,10000))-100 | L31: =K31-H31 | M31: =IF(K31=0,0,L31/K31) | O31: Lista | P31: imagenes/UN50U8000HPXPA.jpg
A32: UN65U8000HPXPA | B32: Televisor Samsung 65" Crystal UHD 4K U8000H | C32: TV y consolas | D32: Televisores | E32: Samsung | G32: Sin control | H32: 1999900 | I32: =INDEX(Márgenes!$C$7:$C$23,MATCH(D32,Márgenes!$B$7:$B$23,0)) | J32: =MAX(H32*(1+I32),H32+Márgenes!$B$4) | K32: =IF(J32<1000000,CEILING(J32,1000),CEILING(J32,10000))-100 | L32: =K32-H32 | M32: =IF(K32=0,0,L32/K32) | O32: Lista | P32: imagenes/UN65U8000HPXPA.jpg
A33: 82XQ00EBUS | B33: Lenovo IdeaPad Slim 3 15.6" Ryzen 5 7520U | C33: Computación | D33: Portátiles | E33: Lenovo | G33: 3 | H33: 1448405 | I33: =INDEX(Márgenes!$C$7:$C$23,MATCH(D33,Márgenes!$B$7:$B$23,0)) | J33: =MAX(H33*(1+I33),H33+Márgenes!$B$4) | K33: =IF(J33<1000000,CEILING(J33,1000),CEILING(J33,10000))-100 | L33: =K33-H33 | M33: =IF(K33=0,0,L33/K33) | O33: Lista | P33: imagenes/82XQ00EBUS.jpg
A34: 82XB00BMUS | B34: Lenovo IdeaPad Slim 3i 15.6" Core i3 N305 | C34: Computación | D34: Portátiles | E34: Lenovo | G34: 3 | H34: 1357809 | I34: =INDEX(Márgenes!$C$7:$C$23,MATCH(D34,Márgenes!$B$7:$B$23,0)) | J34: =MAX(H34*(1+I34),H34+Márgenes!$B$4) | K34: =IF(J34<1000000,CEILING(J34,1000),CEILING(J34,10000))-100 | L34: =K34-H34 | M34: =IF(K34=0,0,L34/K34) | O34: Lista | P34: imagenes/82XB00BMUS.jpg
A35: 83J1002KUS | B35: Lenovo IdeaPad Slim 5i 16" Táctil Core 7 240H | C35: Computación | D35: Portátiles | E35: Lenovo | G35: 1 | H35: 2677758 | I35: =INDEX(Márgenes!$C$7:$C$23,MATCH(D35,Márgenes!$B$7:$B$23,0)) | J35: =MAX(H35*(1+I35),H35+Márgenes!$B$4) | K35: =IF(J35<1000000,CEILING(J35,1000),CEILING(J35,10000))-100 | L35: =K35-H35 | M35: =IF(K35=0,0,L35/K35) | O35: Lista | P35: imagenes/83J1002KUS.jpg
A36: 83A100PBUS | B36: Lenovo 15.6" Core i3-1315U | C36: Computación | D36: Portátiles | E36: Lenovo | G36: 10 | H36: 1533239 | I36: =INDEX(Márgenes!$C$7:$C$23,MATCH(D36,Márgenes!$B$7:$B$23,0)) | J36: =MAX(H36*(1+I36),H36+Márgenes!$B$4) | K36: =IF(J36<1000000,CEILING(J36,1000),CEILING(J36,10000))-100 | L36: =K36-H36 | M36: =IF(K36=0,0,L36/K36) | O36: Lista | P36: imagenes/83A100PBUS.jpg
A37: 16-BU0305DX | B37: HP OmniBook 3 16" Táctil Core Ultra 5 225U | C37: Computación | D37: Portátiles | E37: HP | G37: 5 | H37: 1866191 | I37: =INDEX(Márgenes!$C$7:$C$23,MATCH(D37,Márgenes!$B$7:$B$23,0)) | J37: =MAX(H37*(1+I37),H37+Márgenes!$B$4) | K37: =IF(J37<1000000,CEILING(J37,1000),CEILING(J37,10000))-100 | L37: =K37-H37 | M37: =IF(K37=0,0,L37/K37) | O37: Lista | P37: imagenes/16-BU0305DX.jpg
A38: 15-FD0127DX | B38: HP 15.6" Táctil FHD Core 7 150U | C38: Computación | D38: Portátiles | E38: HP | G38: 3 | H38: 2332429 | I38: =INDEX(Márgenes!$C$7:$C$23,MATCH(D38,Márgenes!$B$7:$B$23,0)) | J38: =MAX(H38*(1+I38),H38+Márgenes!$B$4) | K38: =IF(J38<1000000,CEILING(J38,1000),CEILING(J38,10000))-100 | L38: =K38-H38 | M38: =IF(K38=0,0,L38/K38) | O38: Lista | P38: imagenes/15-FD0127DX.jpg
A39: 14-DQ6101DX | B39: HP 14" HD Intel N150 | C39: Computación | D39: Portátiles | E39: HP | G39: 10 | H39: 826083 | I39: =INDEX(Márgenes!$C$7:$C$23,MATCH(D39,Márgenes!$B$7:$B$23,0)) | J39: =MAX(H39*(1+I39),H39+Márgenes!$B$4) | K39: =IF(J39<1000000,CEILING(J39,1000),CEILING(J39,10000))-100 | L39: =K39-H39 | M39: =IF(K39=0,0,L39/K39) | O39: Lista | P39: imagenes/14-DQ6101DX.jpg
A40: LDC15250-5434BLK-PUS | B40: Dell Inspiron 15 Táctil FHD Core i5-1334U | C40: Computación | D40: Portátiles | E40: Dell | G40: 6 | H40: 1769417 | I40: =INDEX(Márgenes!$C$7:$C$23,MATCH(D40,Márgenes!$B$7:$B$23,0)) | J40: =MAX(H40*(1+I40),H40+Márgenes!$B$4) | K40: =IF(J40<1000000,CEILING(J40,1000),CEILING(J40,10000))-100 | L40: =K40-H40 | M40: =IF(K40=0,0,L40/K40) | O40: Lista | P40: imagenes/LDC15250-5434BLK-PUS.jpg
A41: DC15250 | B41: Dell Inspiron 15 FHD Core 3 100U | C41: Computación | D41: Portátiles | E41: Dell | G41: 2 | H41: 1482206 | I41: =INDEX(Márgenes!$C$7:$C$23,MATCH(D41,Márgenes!$B$7:$B$23,0)) | J41: =MAX(H41*(1+I41),H41+Márgenes!$B$4) | K41: =IF(J41<1000000,CEILING(J41,1000),CEILING(J41,10000))-100 | L41: =K41-H41 | M41: =IF(K41=0,0,L41/K41) | O41: Lista | P41: imagenes/DC15250.jpg
A42: F1504MA-SS51-Q | B42: Asus Vivobook 15 FHD Core 5 320 | C42: Computación | D42: Portátiles | E42: Asus | G42: 6 | H42: 1750735 | I42: =INDEX(Márgenes!$C$7:$C$23,MATCH(D42,Márgenes!$B$7:$B$23,0)) | J42: =MAX(H42*(1+I42),H42+Márgenes!$B$4) | K42: =IF(J42<1000000,CEILING(J42,1000),CEILING(J42,10000))-100 | L42: =K42-H42 | M42: =IF(K42=0,0,L42/K42) | O42: Lista | P42: imagenes/F1504MA-SS51-Q.jpg
A43: L3310 | B43: Impresora Epson EcoTank L3310 | C43: Computación | D43: Impresoras | E43: Epson | G43: Sin control | H43: 714000 | I43: =INDEX(Márgenes!$C$7:$C$23,MATCH(D43,Márgenes!$B$7:$B$23,0)) | J43: =MAX(H43*(1+I43),H43+Márgenes!$B$4) | K43: =IF(J43<1000000,CEILING(J43,1000),CEILING(J43,10000))-100 | L43: =K43-H43 | M43: =IF(K43=0,0,L43/K43) | O43: Lista | P43: imagenes/L3310.jpg
A44: JBL-ENDRUN3 | B44: JBL Endurance Run 3 | C44: Audio | D44: Audífonos | E44: JBL | G44: Sin control | H44: 95000 | I44: =INDEX(Márgenes!$C$7:$C$23,MATCH(D44,Márgenes!$B$7:$B$23,0)) | J44: =MAX(H44*(1+I44),H44+Márgenes!$B$4) | K44: =IF(J44<1000000,CEILING(J44,1000),CEILING(J44,10000))-100 | L44: =K44-H44 | M44: =IF(K44=0,0,L44/K44) | O44: Lista | P44: imagenes/JBL-ENDRUN3.jpg
A45: JBL-WAVEBUDS2 | B45: JBL Wave Buds 2 | C45: Audio | D45: Audífonos | E45: JBL | G45: Sin control | H45: 145400 | I45: =INDEX(Márgenes!$C$7:$C$23,MATCH(D45,Márgenes!$B$7:$B$23,0)) | J45: =MAX(H45*(1+I45),H45+Márgenes!$B$4) | K45: =IF(J45<1000000,CEILING(J45,1000),CEILING(J45,10000))-100 | L45: =K45-H45 | M45: =IF(K45=0,0,L45/K45) | O45: Lista | P45: imagenes/JBL-WAVEBUDS2.jpg
A46: JBL-CLIP5 | B46: JBL Clip 5 | C46: Audio | D46: Parlantes | E46: JBL | G46: Sin control | H46: 169800 | I46: =INDEX(Márgenes!$C$7:$C$23,MATCH(D46,Márgenes!$B$7:$B$23,0)) | J46: =MAX(H46*(1+I46),H46+Márgenes!$B$4) | K46: =IF(J46<1000000,CEILING(J46,1000),CEILING(J46,10000))-100 | L46: =K46-H46 | M46: =IF(K46=0,0,L46/K46) | O46: Lista | P46: imagenes/JBL-CLIP5.jpg
A47: JBL-GRIP | B47: JBL Grip | C47: Audio | D47: Parlantes | E47: JBL | G47: Sin control | H47: 230000 | I47: =INDEX(Márgenes!$C$7:$C$23,MATCH(D47,Márgenes!$B$7:$B$23,0)) | J47: =MAX(H47*(1+I47),H47+Márgenes!$B$4) | K47: =IF(J47<1000000,CEILING(J47,1000),CEILING(J47,10000))-100 | L47: =K47-H47 | M47: =IF(K47=0,0,L47/K47) | O47: Lista | P47: imagenes/JBL-GRIP.jpg
A48: JBL-FLIP7 | B48: JBL Flip 7 | C48: Audio | D48: Parlantes | E48: JBL | G48: Sin control | H48: 365000 | I48: =INDEX(Márgenes!$C$7:$C$23,MATCH(D48,Márgenes!$B$7:$B$23,0)) | J48: =MAX(H48*(1+I48),H48+Márgenes!$B$4) | K48: =IF(J48<1000000,CEILING(J48,1000),CEILING(J48,10000))-100 | L48: =K48-H48 | M48: =IF(K48=0,0,L48/K48) | O48: Lista | P48: imagenes/JBL-FLIP7.jpg
A49: JBL-CHARGE6 | B49: JBL Charge 6 | C49: Audio | D49: Parlantes | E49: JBL | G49: Sin control | H49: 520000 | I49: =INDEX(Márgenes!$C$7:$C$23,MATCH(D49,Márgenes!$B$7:$B$23,0)) | J49: =MAX(H49*(1+I49),H49+Márgenes!$B$4) | K49: =IF(J49<1000000,CEILING(J49,1000),CEILING(J49,10000))-100 | L49: =K49-H49 | M49: =IF(K49=0,0,L49/K49) | O49: Lista | P49: imagenes/JBL-CHARGE6.jpg
A50: JBL-TUNE530BT | B50: JBL Tune 530BT | C50: Audio | D50: Audífonos | E50: JBL | G50: Sin control | H50: 125000 | I50: =INDEX(Márgenes!$C$7:$C$23,MATCH(D50,Márgenes!$B$7:$B$23,0)) | J50: =MAX(H50*(1+I50),H50+Márgenes!$B$4) | K50: =IF(J50<1000000,CEILING(J50,1000),CEILING(J50,10000))-100 | L50: =K50-H50 | M50: =IF(K50=0,0,L50/K50) | O50: Lista | P50: imagenes/JBL-TUNE530BT.jpg
A51: JBL-TUNE730BT | B51: JBL Tune 730BT | C51: Audio | D51: Audífonos | E51: JBL | G51: Sin control | H51: 169900 | I51: =INDEX(Márgenes!$C$7:$C$23,MATCH(D51,Márgenes!$B$7:$B$23,0)) | J51: =MAX(H51*(1+I51),H51+Márgenes!$B$4) | K51: =IF(J51<1000000,CEILING(J51,1000),CEILING(J51,10000))-100 | L51: =K51-H51 | M51: =IF(K51=0,0,L51/K51) | O51: Lista | P51: imagenes/JBL-TUNE730BT.jpg
A52: JBL-PBCLUB120 | B52: JBL PartyBox Club 120 | C52: Audio | D52: Parlantes | E52: JBL | G52: Sin control | H52: 1150000 | I52: =INDEX(Márgenes!$C$7:$C$23,MATCH(D52,Márgenes!$B$7:$B$23,0)) | J52: =MAX(H52*(1+I52),H52+Márgenes!$B$4) | K52: =IF(J52<1000000,CEILING(J52,1000),CEILING(J52,10000))-100 | L52: =K52-H52 | M52: =IF(K52=0,0,L52/K52) | O52: Lista | P52: imagenes/JBL-PBCLUB120.jpg
A53: XIA-SOUNDPOCKET | B53: Parlante Xiaomi Sound Pocket 5W | C53: Audio | D53: Parlantes | E53: Xiaomi | F53: Negro | G53: Sin control | H53: 50000 | I53: =INDEX(Márgenes!$C$7:$C$23,MATCH(D53,Márgenes!$B$7:$B$23,0)) | J53: =MAX(H53*(1+I53),H53+Márgenes!$B$4) | K53: =IF(J53<1000000,CEILING(J53,1000),CEILING(J53,10000))-100 | L53: =K53-H53 | M53: =IF(K53=0,0,L53/K53) | O53: Lista | P53: imagenes/XIA-SOUNDPOCKET.jpg
A54: XIA-SOUNDPARTY | B54: Parlante Xiaomi Sound Party | C54: Audio | D54: Parlantes | E54: Xiaomi | F54: Negro | G54: 2 | H54: 260000 | I54: =INDEX(Márgenes!$C$7:$C$23,MATCH(D54,Márgenes!$B$7:$B$23,0)) | J54: =MAX(H54*(1+I54),H54+Márgenes!$B$4) | K54: =IF(J54<1000000,CEILING(J54,1000),CEILING(J54,10000))-100 | L54: =K54-H54 | M54: =IF(K54=0,0,L54/K54) | O54: Lista | P54: imagenes/XIA-SOUNDPARTY.jpg
A55: XIA-S29D | B55: Parlante Xiaomi Sound Outdoor 30W (S29D) | C55: Audio | D55: Parlantes | E55: Xiaomi | F55: Negro, Rojo, Azul | G55: Sin control | H55: 135000 | I55: =INDEX(Márgenes!$C$7:$C$23,MATCH(D55,Márgenes!$B$7:$B$23,0)) | J55: =MAX(H55*(1+I55),H55+Márgenes!$B$4) | K55: =IF(J55<1000000,CEILING(J55,1000),CEILING(J55,10000))-100 | L55: =K55-H55 | M55: =IF(K55=0,0,L55/K55) | O55: Lista | P55: imagenes/XIA-S29D.jpg
A56: XIA-BUDS8ACT | B56: Redmi Buds 8 Active | C56: Audio | D56: Audífonos | E56: Xiaomi | F56: Negro, Azul | G56: Sin control | H56: 69000 | I56: =INDEX(Márgenes!$C$7:$C$23,MATCH(D56,Márgenes!$B$7:$B$23,0)) | J56: =MAX(H56*(1+I56),H56+Márgenes!$B$4) | K56: =IF(J56<1000000,CEILING(J56,1000),CEILING(J56,10000))-100 | L56: =K56-H56 | M56: =IF(K56=0,0,L56/K56) | O56: Lista | P56: imagenes/XIA-BUDS8ACT.jpg
A57: XIA-BUDS8 | B57: Redmi Buds 8 | C57: Audio | D57: Audífonos | E57: Xiaomi | F57: Negro, Blanco | G57: Sin control | H57: 152000 | I57: =INDEX(Márgenes!$C$7:$C$23,MATCH(D57,Márgenes!$B$7:$B$23,0)) | J57: =MAX(H57*(1+I57),H57+Márgenes!$B$4) | K57: =IF(J57<1000000,CEILING(J57,1000),CEILING(J57,10000))-100 | L57: =K57-H57 | M57: =IF(K57=0,0,L57/K57) | O57: Lista | P57: imagenes/XIA-BUDS8.jpg
A58: XIA-BUDS8LITE | B58: Redmi Buds 8 Lite | C58: Audio | D58: Audífonos | E58: Xiaomi | F58: Azul, Negro, Blanco | G58: Sin control | H58: 80000 | I58: =INDEX(Márgenes!$C$7:$C$23,MATCH(D58,Márgenes!$B$7:$B$23,0)) | J58: =MAX(H58*(1+I58),H58+Márgenes!$B$4) | K58: =IF(J58<1000000,CEILING(J58,1000),CEILING(J58,10000))-100 | L58: =K58-H58 | M58: =IF(K58=0,0,L58/K58) | O58: Lista | P58: imagenes/XIA-BUDS8LITE.jpg
A59: XIA-BAND11ACT | B59: Xiaomi Smart Band 11 Active | C59: Celulares y tablets | D59: Relojes inteligentes | E59: Xiaomi | F59: Negro | G59: Sin control | H59: 110000 | I59: =INDEX(Márgenes!$C$7:$C$23,MATCH(D59,Márgenes!$B$7:$B$23,0)) | J59: =MAX(H59*(1+I59),H59+Márgenes!$B$4) | K59: =IF(J59<1000000,CEILING(J59,1000),CEILING(J59,10000))-100 | L59: =K59-H59 | M59: =IF(K59=0,0,L59/K59) | O59: Lista | P59: imagenes/XIA-BAND11ACT.jpg
A60: XIA-RWATCH6ACT | B60: Redmi Watch 6 Active | C60: Celulares y tablets | D60: Relojes inteligentes | E60: Xiaomi | F60: Negro, Naranja | G60: Sin control | H60: 140000 | I60: =INDEX(Márgenes!$C$7:$C$23,MATCH(D60,Márgenes!$B$7:$B$23,0)) | J60: =MAX(H60*(1+I60),H60+Márgenes!$B$4) | K60: =IF(J60<1000000,CEILING(J60,1000),CEILING(J60,10000))-100 | L60: =K60-H60 | M60: =IF(K60=0,0,L60/K60) | O60: Lista | P60: imagenes/XIA-RWATCH6ACT.jpg
A61: AUT124 | B61: Audífonos Alámbricos AUT124 | C61: Audio | D61: Audífonos | E61: 1Hora | G61: Sin control | H61: 7216 | I61: =INDEX(Márgenes!$C$7:$C$23,MATCH(D61,Márgenes!$B$7:$B$23,0)) | J61: =MAX(H61*(1+I61),H61+Márgenes!$B$4) | K61: =IF(J61<1000000,CEILING(J61,1000),CEILING(J61,10000))-100 | L61: =K61-H61 | M61: =IF(K61=0,0,L61/K61) | O61: Lista | P61: imagenes/AUT124.jpg
A62: AUT114 | B62: Audífonos Inalámbricos AUT114 | C62: Audio | D62: Audífonos | E62: 1Hora | G62: Sin control | H62: 32939 | I62: =INDEX(Márgenes!$C$7:$C$23,MATCH(D62,Márgenes!$B$7:$B$23,0)) | J62: =MAX(H62*(1+I62),H62+Márgenes!$B$4) | K62: =IF(J62<1000000,CEILING(J62,1000),CEILING(J62,10000))-100 | L62: =K62-H62 | M62: =IF(K62=0,0,L62/K62) | O62: Lista | P62: imagenes/AUT114.jpg
A63: AUT201 | B63: Audífonos Inalámbricos AUT201 | C63: Audio | D63: Audífonos | E63: 1Hora | G63: Sin control | H63: 37993 | I63: =INDEX(Márgenes!$C$7:$C$23,MATCH(D63,Márgenes!$B$7:$B$23,0)) | J63: =MAX(H63*(1+I63),H63+Márgenes!$B$4) | K63: =IF(J63<1000000,CEILING(J63,1000),CEILING(J63,10000))-100 | L63: =K63-H63 | M63: =IF(K63=0,0,L63/K63) | O63: Lista | P63: imagenes/AUT201.jpg
A64: AUT207 | B64: Audífonos Inalámbricos AUT207 | C64: Audio | D64: Audífonos | E64: 1Hora | G64: Sin control | H64: 30400 | I64: =INDEX(Márgenes!$C$7:$C$23,MATCH(D64,Márgenes!$B$7:$B$23,0)) | J64: =MAX(H64*(1+I64),H64+Márgenes!$B$4) | K64: =IF(J64<1000000,CEILING(J64,1000),CEILING(J64,10000))-100 | L64: =K64-H64 | M64: =IF(K64=0,0,L64/K64) | O64: Lista | P64: imagenes/AUT207.jpg
A65: AUT119 | B65: Audífonos AUT119 | C65: Audio | D65: Audífonos | E65: 1Hora | G65: Sin control | H65: 32875 | I65: =INDEX(Márgenes!$C$7:$C$23,MATCH(D65,Márgenes!$B$7:$B$23,0)) | J65: =MAX(H65*(1+I65),H65+Márgenes!$B$4) | K65: =IF(J65<1000000,CEILING(J65,1000),CEILING(J65,10000))-100 | L65: =K65-H65 | M65: =IF(K65=0,0,L65/K65) | O65: Lista | P65: imagenes/AUT119.jpg
A66: AUT208 | B66: Audífonos AUT208 | C66: Audio | D66: Audífonos | E66: 1Hora | G66: Sin control | H66: 29999 | I66: =INDEX(Márgenes!$C$7:$C$23,MATCH(D66,Márgenes!$B$7:$B$23,0)) | J66: =MAX(H66*(1+I66),H66+Márgenes!$B$4) | K66: =IF(J66<1000000,CEILING(J66,1000),CEILING(J66,10000))-100 | L66: =K66-H66 | M66: =IF(K66=0,0,L66/K66) | O66: Lista | P66: imagenes/AUT208.jpg
A67: AUT212 | B67: Audífonos AUT212 | C67: Audio | D67: Audífonos | E67: 1Hora | G67: Sin control | H67: 38124 | I67: =INDEX(Márgenes!$C$7:$C$23,MATCH(D67,Márgenes!$B$7:$B$23,0)) | J67: =MAX(H67*(1+I67),H67+Márgenes!$B$4) | K67: =IF(J67<1000000,CEILING(J67,1000),CEILING(J67,10000))-100 | L67: =K67-H67 | M67: =IF(K67=0,0,L67/K67) | O67: Lista | P67: imagenes/AUT212.jpg
A68: AUT210 | B68: Audífonos AUT210 | C68: Audio | D68: Audífonos | E68: 1Hora | G68: Sin control | H68: 42875 | I68: =INDEX(Márgenes!$C$7:$C$23,MATCH(D68,Márgenes!$B$7:$B$23,0)) | J68: =MAX(H68*(1+I68),H68+Márgenes!$B$4) | K68: =IF(J68<1000000,CEILING(J68,1000),CEILING(J68,10000))-100 | L68: =K68-H68 | M68: =IF(K68=0,0,L68/K68) | O68: Lista | P68: imagenes/AUT210.jpg
A69: AUT216 | B69: Audífonos AUT216 | C69: Audio | D69: Audífonos | E69: 1Hora | G69: Sin control | H69: 37629 | I69: =INDEX(Márgenes!$C$7:$C$23,MATCH(D69,Márgenes!$B$7:$B$23,0)) | J69: =MAX(H69*(1+I69),H69+Márgenes!$B$4) | K69: =IF(J69<1000000,CEILING(J69,1000),CEILING(J69,10000))-100 | L69: =K69-H69 | M69: =IF(K69=0,0,L69/K69) | O69: Lista | P69: imagenes/AUT216.jpg
A70: BOC060 | B70: Parlante Bluetooth BOC060 | C70: Audio | D70: Parlantes | E70: 1Hora | G70: Sin control | H70: 37499 | I70: =INDEX(Márgenes!$C$7:$C$23,MATCH(D70,Márgenes!$B$7:$B$23,0)) | J70: =MAX(H70*(1+I70),H70+Márgenes!$B$4) | K70: =IF(J70<1000000,CEILING(J70,1000),CEILING(J70,10000))-100 | L70: =K70-H70 | M70: =IF(K70=0,0,L70/K70) | O70: Lista | P70: imagenes/BOC060.jpg
A71: BOC242-N | B71: Parlante Bluetooth BOC242 Negro | C71: Audio | D71: Parlantes | E71: 1Hora | G71: Sin control | H71: 37499 | I71: =INDEX(Márgenes!$C$7:$C$23,MATCH(D71,Márgenes!$B$7:$B$23,0)) | J71: =MAX(H71*(1+I71),H71+Márgenes!$B$4) | K71: =IF(J71<1000000,CEILING(J71,1000),CEILING(J71,10000))-100 | L71: =K71-H71 | M71: =IF(K71=0,0,L71/K71) | O71: Lista | P71: imagenes/BOC242-N.jpg
A72: BOC242-R | B72: Parlante Bluetooth BOC242 Rojo | C72: Audio | D72: Parlantes | E72: 1Hora | G72: Sin control | H72: 29999 | I72: =INDEX(Márgenes!$C$7:$C$23,MATCH(D72,Márgenes!$B$7:$B$23,0)) | J72: =MAX(H72*(1+I72),H72+Márgenes!$B$4) | K72: =IF(J72<1000000,CEILING(J72,1000),CEILING(J72,10000))-100 | L72: =K72-H72 | M72: =IF(K72=0,0,L72/K72) | O72: Lista | P72: imagenes/BOC242-R.jpg
... A114: HC150B | B114: Picadora de Alimentos Black+Decker HC150B | C114: Hogar | D114: Electrodomésticos | E114: Black+Decker | G114: Sin control | H114: 65930 | I114: =INDEX(Márgenes!$C$7:$C$23,MATCH(D114,Márgenes!$B$7:$B$23,0)) | J114: =MAX(H114*(1+I114),H114+Márgenes!$B$4) | K114: =IF(J114<1000000,CEILING(J114,1000),CEILING(J114,10000))-100 | L114: =K114-H114 | M114: =IF(K114=0,0,L114/K114) | O114: Lista | P114: imagenes/HC150B.jpg
A115: IRBD365 | B115: Plancha de Vapor Black+Decker IRBD365 Cable Retráctil | C115: Hogar | D115: Electrodomésticos | E115: Black+Decker | F115: Azul | G115: Sin control | H115: 51539 | I115: =INDEX(Márgenes!$C$7:$C$23,MATCH(D115,Márgenes!$B$7:$B$23,0)) | J115: =MAX(H115*(1+I115),H115+Márgenes!$B$4) | K115: =IF(J115<1000000,CEILING(J115,1000),CEILING(J115,10000))-100 | L115: =K115-H115 | M115: =IF(K115=0,0,L115/K115) | O115: Lista | P115: imagenes/IRBD365.jpg
A116: F54 | B116: Plancha Black+Decker F54 Cable Retráctil | C116: Hogar | D116: Electrodomésticos | E116: Black+Decker | G116: Sin control | H116: 55665 | I116: =INDEX(Márgenes!$C$7:$C$23,MATCH(D116,Márgenes!$B$7:$B$23,0)) | J116: =MAX(H116*(1+I116),H116+Márgenes!$B$4) | K116: =IF(J116<1000000,CEILING(J116,1000),CEILING(J116,10000))-100 | L116: =K116-H116 | M116: =IF(K116=0,0,L116/K116) | O116: Lista | P116: imagenes/F54.jpg
A117: IR1866 | B117: Plancha de Vapor Black+Decker IR1866 Cable Retráctil | C117: Hogar | D117: Electrodomésticos | E117: Black+Decker | G117: Sin control | H117: 65440 | I117: =INDEX(Márgenes!$C$7:$C$23,MATCH(D117,Márgenes!$B$7:$B$23,0)) | J117: =MAX(H117*(1+I117),H117+Márgenes!$B$4) | K117: =IF(J117<1000000,CEILING(J117,1000),CEILING(J117,10000))-100 | L117: =K117-H117 | M117: =IF(K117=0,0,L117/K117) | O117: Lista | P117: imagenes/IR1866.jpg
A118: CS-H1C-R101-1G2WR | B118: Cámara Ezviz H1C Interior | C118: Hogar | D118: Cámaras de seguridad | E118: Ezviz | G118: Sin control | H118: 79515 | I118: =INDEX(Márgenes!$C$7:$C$23,MATCH(D118,Márgenes!$B$7:$B$23,0)) | J118: =MAX(H118*(1+I118),H118+Márgenes!$B$4) | K118: =IF(J118<1000000,CEILING(J118,1000),CEILING(J118,10000))-100 | L118: =K118-H118 | M118: =IF(K118=0,0,L118/K118) | O118: Lista | P118: imagenes/CS-H1C-R101-1G2WR.jpg
A119: CS-H6C-R200-1Q5WFL | B119: Cámara Ezviz H6C Interior (R200) | C119: Hogar | D119: Cámaras de seguridad | E119: Ezviz | G119: Sin control | H119: 133144 | I119: =INDEX(Márgenes!$C$7:$C$23,MATCH(D119,Márgenes!$B$7:$B$23,0)) | J119: =MAX(H119*(1+I119),H119+Márgenes!$B$4) | K119: =IF(J119<1000000,CEILING(J119,1000),CEILING(J119,10000))-100 | L119: =K119-H119 | M119: =IF(K119=0,0,L119/K119) | O119: Lista | P119: imagenes/CS-H6C-R200-1Q5WFL.jpg
A120: CS-H6C-R105-1L3WF | B120: Cámara Ezviz H6C Interior (R105) | C120: Hogar | D120: Cámaras de seguridad | E120: Ezviz | G120: 1 | H120: 114312 | I120: =INDEX(Márgenes!$C$7:$C$23,MATCH(D120,Márgenes!$B$7:$B$23,0)) | J120: =MAX(H120*(1+I120),H120+Márgenes!$B$4) | K120: =IF(J120<1000000,CEILING(J120,1000),CEILING(J120,10000))-100 | L120: =K120-H120 | M120: =IF(K120=0,0,L120/K120) | O120: Lista | P120: imagenes/CS-H6C-R105-1L3WF.jpg
A121: CS-H8C-R200-1K3WKFL | B121: Cámara Ezviz H8C Exterior | C121: Hogar | D121: Cámaras de seguridad | E121: Ezviz | G121: 1 | H121: 181561 | I121: =INDEX(Márgenes!$C$7:$C$23,MATCH(D121,Márgenes!$B$7:$B$23,0)) | J121: =MAX(H121*(1+I121),H121+Márgenes!$B$4) | K121: =IF(J121<1000000,CEILING(J121,1000),CEILING(J121,10000))-100 | L121: =K121-H121 | M121: =IF(K121=0,0,L121/K121) | O121: Lista | P121: imagenes/CS-H8C-R200-1K3WKFL.jpg
G123: Totales | H123: =SUM(H2:H121) | K123: =SUM(K2:K121) | L123: =SUM(L2:L121) | M123: =IF(K123=0,0,L123/K123)

Sheet Márgenes
A1: Márgenes por subcategoría
A2: Edita las celdas amarillas: los precios de la hoja Productos se recalculan solos.
A4: Ganancia mínima por unidad (COP) | B4: 12000
A6: Categoría | B6: Subcategoría | C6: Margen sobre costo | D6: Productos
A7: Accesorios | B7: Cables | C7: 1 | D7: =COUNTIF(Productos!$D:$D,B7)
A8: Accesorios | B8: Cargadores | C8: 0.8 | D8: =COUNTIF(Productos!$D:$D,B8)
A9: Accesorios | B9: Power banks | C9: 0.6 | D9: =COUNTIF(Productos!$D:$D,B9)
A10: Audio | B10: Audífonos | C10: 0.35 | D10: =COUNTIF(Productos!$D:$D,B10)
A11: Audio | B11: Parlantes | C11: 0.3 | D11: =COUNTIF(Productos!$D:$D,B11)
A12: Celulares y tablets | B12: Celulares | C12: 0.15 | D12: =COUNTIF(Productos!$D:$D,B12)
A13: Celulares y tablets | B13: Relojes inteligentes | C13: 0.3 | D13: =COUNTIF(Productos!$D:$D,B13)
A14: Celulares y tablets | B14: Tablets | C14: 0.18 | D14: =COUNTIF(Productos!$D:$D,B14)
A15: Computación | B15: Impresoras | C15: 0.15 | D15: =COUNTIF(Productos!$D:$D,B15)
A16: Computación | B16: Periféricos | C16: 0.8 | D16: =COUNTIF(Productos!$D:$D,B16)
A17: Computación | B17: Portátiles | C17: 0.12 | D17: =COUNTIF(Productos!$D:$D,B17)
A18: Hogar | B18: Cámaras de seguridad | C18: 0.35 | D18: =COUNTIF(Productos!$D:$D,B18)
... A23: TV y consolas | B23: Televisores | C23: 0.12 | D23: =COUNTIF(Productos!$D:$D,B23)

Sheet Notas
A1: Cómo se calcula el precio
A2: Precio sin redondear = el mayor entre: costo × (1 + margen de la subcategoría) y costo + ganancia mínima.
A3: Precio de venta = se redondea hacia arriba y termina en 900 (al millar por debajo de $1.000.000; a la decena de mil por encima).
A5: De dónde salen los datos
A6: Costo proveedor: "Precio de Venta" del archivo Catalogo_Dropshipping.xlsx (lista del proveedor, sin modificar), según indicó el usuario.
A7: Márgenes y ganancia mínima: propuesta inicial de Zeltron; ajústalos en la hoja Márgenes.
A8: Colores y unidades: extraídos de la descripción original. Productos con más de un color se crean como producto variable (un precio, varios colores).
A9: Categorías: las 14 del archivo se agruparon en 7 categorías con subcategorías para el menú de la tienda.
A11: Importante
A12: El archivo catalogo-woocommerce.csv ya trae los precios con los márgenes de esta versión.
A13: Si cambias márgenes aquí, pide regenerar el CSV, o ajusta el precio directamente en WooCommerce.
A14: No se crearon precios "antes" ni descuentos: la tienda solo muestra ofertas reales que cargues en "Precio rebajado".
... A19: Para subirlas a la tienda: arrastra la carpeta de imágenes a WordPress → Medios → Añadir nuevo, y luego importa catalogo-imagenes-woocommerce.csv con «Actualizar productos existentes» activado.
